collective.contentrules.mailtogroup-1.6-py2.7-nspkg.pth
collective/contentrules/mailtogroup/__init__.py
collective/contentrules/mailtogroup/configure.zcml
collective/contentrules/mailtogroup/actions/__init__.py
collective/contentrules/mailtogroup/actions/configure.zcml
collective/contentrules/mailtogroup/actions/mail.py
collective/contentrules/mailtogroup/actions/templates/mail.pt
collective/contentrules/mailtogroup/actions_formlib/__init__.py
collective/contentrules/mailtogroup/actions_formlib/configure.zcml
collective/contentrules/mailtogroup/actions_formlib/mail.py
collective/contentrules/mailtogroup/locales/collective.contentrules.mailtogroup.pot
collective/contentrules/mailtogroup/locales/plone.pot
collective/contentrules/mailtogroup/locales/en/LC_MESSAGES/collective.contentrules.mailtogroup.mo
collective/contentrules/mailtogroup/locales/en/LC_MESSAGES/collective.contentrules.mailtogroup.po
collective/contentrules/mailtogroup/locales/es/LC_MESSAGES/collective.contentrules.mailtogroup.mo
collective/contentrules/mailtogroup/locales/es/LC_MESSAGES/collective.contentrules.mailtogroup.po
collective/contentrules/mailtogroup/locales/es/LC_MESSAGES/plone.mo
collective/contentrules/mailtogroup/locales/es/LC_MESSAGES/plone.po
collective/contentrules/mailtogroup/locales/nl/LC_MESSAGES/collective.contentrules.mailtogroup.mo
collective/contentrules/mailtogroup/locales/nl/LC_MESSAGES/collective.contentrules.mailtogroup.po
collective/contentrules/mailtogroup/locales/pt_BR/LC_MESSAGES/collective.contentrules.mailtogroup.mo
collective/contentrules/mailtogroup/locales/pt_BR/LC_MESSAGES/collective.contentrules.mailtogroup.po
collective/contentrules/mailtogroup/locales/pt_BR/LC_MESSAGES/plone.mo
collective/contentrules/mailtogroup/locales/pt_BR/LC_MESSAGES/plone.po
collective/contentrules/mailtogroup/tests/__init__.py
collective/contentrules/mailtogroup/tests/dummymailhost.py
collective/contentrules/mailtogroup/tests/test_action_mail_to_group.py
collective.contentrules.mailtogroup-1.6.dist-info/DESCRIPTION.rst
collective.contentrules.mailtogroup-1.6.dist-info/METADATA
collective.contentrules.mailtogroup-1.6.dist-info/RECORD
collective.contentrules.mailtogroup-1.6.dist-info/WHEEL
collective.contentrules.mailtogroup-1.6.dist-info/entry_points.txt
collective.contentrules.mailtogroup-1.6.dist-info/metadata.json
collective.contentrules.mailtogroup-1.6.dist-info/namespace_packages.txt
collective.contentrules.mailtogroup-1.6.dist-info/top_level.txt
