Metadata-Version: 2.0
Name: collective.contentrules.mailtogroup
Version: 1.6
Summary: Send e-mail to groups and members defined in the action.
Home-page: http://www.gw20e.com/
Author: Goldmund, Wyldebeast & Wunderliebe (K.C. Leong)
Author-email: leong@gw20e.com
License: UNKNOWN
Keywords: plone automatic content rules
Platform: UNKNOWN
Classifier: Development Status :: 5 - Production/Stable
Classifier: Environment :: Web Environment
Classifier: Framework :: Plone :: 4.3
Classifier: Framework :: Plone :: 5.0
Classifier: Framework :: Plone :: 5.1
Classifier: Framework :: Plone
Classifier: Intended Audience :: System Administrators
Classifier: License :: OSI Approved :: GNU General Public License v2 (GPLv2)
Classifier: Operating System :: OS Independent
Classifier: Programming Language :: Python :: 2.7
Classifier: Programming Language :: Python
Classifier: Topic :: Software Development :: Libraries :: Python Modules
Requires-Dist: Products.CMFCore
Requires-Dist: Products.CMFPlone
Requires-Dist: plone.api
Requires-Dist: plone.app.contentrules
Requires-Dist: plone.app.form (>=1.1.8plone.app.vocabularies)
Requires-Dist: plone.contentrules
Requires-Dist: plone.principalsource
Requires-Dist: setuptools
Requires-Dist: zope.component
Requires-Dist: zope.i18nmessageid
Requires-Dist: zope.interface
Requires-Dist: zope.schema
Provides-Extra: test
Requires-Dist: Products.MailHost; extra == 'test'
Requires-Dist: Products.PloneTestCase; extra == 'test'
Requires-Dist: Products.SecureMailHost; extra == 'test'
Requires-Dist: plone.app.robotframework; extra == 'test'
Requires-Dist: plone.app.testing[robot]; extra == 'test'
Requires-Dist: robotsuite; extra == 'test'
